kdaHDFE/Result.py
kdaHDFE/__init__.py
kdaHDFE/calculate_df.py
kdaHDFE/clustering.py
kdaHDFE/demean.py
kdaHDFE/formula_transform.py
kdaHDFE/kdaHDFE.py
kdaHDFE/robust_error.py
kdaHDFE/legacy/AlphaStdErr.py
kdaHDFE/legacy/Bootstrap.py
kdaHDFE/legacy/CalFullModel.py
kdaHDFE/legacy/DemeanDataframe.py
kdaHDFE/legacy/EstimableCheck.py
kdaHDFE/legacy/Forg.py
kdaHDFE/legacy/GetFixedEffect.py
kdaHDFE/legacy/OLSFixed.py
kdaHDFE/legacy/OLSHighDCategory.py
kdaHDFE/legacy/Operation.py
kdaHDFE/legacy/Projection.py
kdaHDFE/legacy/WaldTest.py
kdaHDFE/legacy/__init__.py
kdaHDFE/legacy/to_latex.py
kdaHDFE-0.6.0.dist-info/LICENSE.txt
kdaHDFE-0.6.0.dist-info/METADATA
kdaHDFE-0.6.0.dist-info/WHEEL
kdaHDFE-0.6.0.dist-info/top_level.txt
kdaHDFE-0.6.0.dist-info/RECORD
